dataquant/__init__.py
dataquant/apis/__init__.py
dataquant/apis/base/__init__.py
dataquant/apis/base/api.py
dataquant/apis/info/__init__.py
dataquant/apis/info/api.py
dataquant/apis/quote/__init__.py
dataquant/apis/quote/api.py
dataquant/cd/__init__.py
dataquant/cd/api.py
dataquant/hk/__init__.py
dataquant/hk/api.py
dataquant/ibank/__init__.py
dataquant/ibank/api.py
dataquant/ic/__init__.py
dataquant/ic/api.py
dataquant/intl/__init__.py
dataquant/intl/api.py
dataquant/pof/__init__.py
dataquant/pof/api.py
dataquant/sql/__init__.py
dataquant/sql/api.py
dataquant/utils/__init__.py
dataquant/utils/client.py
dataquant/utils/common.py
dataquant/utils/config.py
dataquant/utils/config.yml
dataquant/utils/connection.py
dataquant/utils/connection_pool.py
dataquant/utils/consts.py
dataquant/utils/convert.py
dataquant/utils/datetime_func.py
dataquant/utils/decorators.py
dataquant/utils/error.py
dataquant/utils/parallel.py
dataquant-1.2.1.dist-info/METADATA
dataquant-1.2.1.dist-info/WHEEL
dataquant-1.2.1.dist-info/entry_points.txt
dataquant-1.2.1.dist-info/top_level.txt
dataquant-1.2.1.dist-info/RECORD
